geospatial_toolkit/__init__.py
geospatial_toolkit/version.py
geospatial_toolkit-0.0.0.dist-info/LICENSE
geospatial_toolkit-0.0.0.dist-info/METADATA
geospatial_toolkit-0.0.0.dist-info/WHEEL
geospatial_toolkit-0.0.0.dist-info/top_level.txt
geospatial_toolkit-0.0.0.dist-info/RECORD
